{
	"name": "ds_src_csv",
	"properties": {
		"linkedServiceName": {
			"referenceName": "ls_adls_retail",
			"type": "LinkedServiceReference"
		},
		"parameters": {
			"p_folder": {
				"type": "string"
			},
			"p_file": {
				"type": "string"
			}
		},
		"annotations": [],
		"type": "DelimitedText",
		"typeProperties": {
			"location": {
				"type": "AzureBlobFSLocation",
				"fileName": {
					"value": "@dataset().p_file",
					"type": "Expression"
				},
				"folderPath": {
					"value": "@dataset().p_folder",
					"type": "Expression"
				},
				"fileSystem": "retaildatalake"
			},
			"columnDelimiter": ",",
			"escapeChar": "\\",
			"firstRowAsHeader": true,
			"quoteChar": "\""
		},
		"schema": [
			{
				"name": "source_entity",
				"type": "String"
			},
			{
				"name": "source_folder",
				"type": "String"
			},
			{
				"name": "source_format",
				"type": "String"
			},
			{
				"name": "sink_folder",
				"type": "String"
			},
			{
				"name": "load_enabled",
				"type": "String"
			}
		]
	}
}